spinne/__init__.py
spinne/__main__.py
spinne/app.py
spinne/css.py
spinne/index.py
spinne/main.py
spinne/views.py
spinne-1.0.0.dist-info/LICENSE
spinne-1.0.0.dist-info/METADATA
spinne-1.0.0.dist-info/WHEEL
spinne-1.0.0.dist-info/top_level.txt
spinne-1.0.0.dist-info/RECORD
